setup.py
jfb_balabala/__init__.py
jfb_balabala/code1.py
jfb_balabala/code2.py
jfb_balabala.egg-info/PKG-INFO
jfb_balabala.egg-info/SOURCES.txt
jfb_balabala.egg-info/dependency_links.txt
jfb_balabala.egg-info/requires.txt
jfb_balabala.egg-info/top_level.txt