Metadata-Version: 1.0
Name: jfb-balabala
Version: 1.0.0
Summary: 模块描述
Home-page: https://github.com/LiangjunFeng/SICA
Author: Jiang Fubang
Author-email: luckybang@163.com
License: MIT Licence
Keywords: pip,balabala,jfb
Platform: any
